Metadata-Version: 2.1
Name: rupdater
Version: 1.1.1a2
Summary: Lightweight dependency free update software
Home-page: https://github.com/r4nx/rupdater
Author: Ranx
Author-email: mod34@yandex.ru
License: GPLv3
Keywords: update,updater
Platform: UNKNOWN
Classifier: Development Status :: 3 - Alpha
Classifier: Intended Audience :: Developers
Classifier: License :: OSI Approved :: GNU General Public License v3 (GPLv3)
Classifier: Programming Language :: Python :: 3.7
Classifier: Topic :: Software Development :: Libraries
Requires-Python: >=3.5
